setup.cfg
setup.py
glu/__init__.py
glu/__main__.py
glu/cli.py
glu/core.py
glu/filter.py
glu/test.py
glu/util.py
glu.egg-info/PKG-INFO
glu.egg-info/SOURCES.txt
glu.egg-info/dependency_links.txt
glu.egg-info/entry_points.txt
glu.egg-info/requires.txt
glu.egg-info/top_level.txt