Metadata-Version: 1.1
Name: glu
Version: 0.0.4
Summary: Glue for DRY configurations
Home-page: UNKNOWN
Author: Park Jong Bin
Author-email: chongkong94@gmail.com
License: UNKNOWN
Keywords: glue,glu,dry,config,dry-config,dry-configurable
Platform: UNKNOWN
Classifier: Programming Language :: Python
Classifier: Programming Language :: Python :: 3.5
Classifier: Development Status :: 2 - Pre-Alpha
Classifier: Intended Audience :: Developers
Classifier: License :: OSI Approved :: MIT License
